qqweibo
